LICENSE.txt
README.md
setup.py
pyqtools/pyqd.py
pyqtools/pyqmdump.py
pyqtools/pyqread.py
pyqtools/pyqsettime.py
pyquaero/__init__.py
pyquaero/backend.py
pyquaero/core.py
pyquaero/server.py
pyquaero/usb.py
pyquaero.egg-info/PKG-INFO
pyquaero.egg-info/SOURCES.txt
pyquaero.egg-info/dependency_links.txt
pyquaero.egg-info/entry_points.txt
pyquaero.egg-info/requires.txt
pyquaero.egg-info/top_level.txt
pyquaero/struct/__init__.py
pyquaero/struct/serializer.py
pyquaero/struct/struct1013.py
pyquaero/struct/struct1200.py
pyquaero/struct/type.py