Metadata-Version: 2.1
Name: pyquaero
Version: 1.3.2
Summary: Library, tools and server for Aquaero cooler controllers
Home-page: https://github.com/shred/pyquaero
Author: Richard Körber
Author-email: dev@shredzone.de
License: GPLv3+
Project-URL: Documentation, https://shredzone.org/docs/pyquaero/index.html
Project-URL: Source, https://github.com/shred/pyquaero
Project-URL: Tracker, https://github.com/shred/pyquaero/issues
Keywords: library server aquaero cooling usb
Platform: UNKNOWN
Classifier: Development Status :: 5 - Production/Stable
Classifier: Intended Audience :: Developers
Classifier: Intended Audience :: System Administrators
Classifier: License :: OSI Approved :: GNU General Public License v3 or later (GPLv3+)
Classifier: Operating System :: OS Independent
Classifier: Programming Language :: Python :: 3 :: Only
Classifier: Topic :: Software Development :: Libraries
Classifier: Topic :: System :: Hardware :: Hardware Drivers
Classifier: Topic :: System :: Monitoring
Classifier: Topic :: Utilities
Requires-Python: >=3
License-File: LICENSE.txt
